fuocli/__init__.py
fuocli/__main__.py
fuocli-1.0.2.dist-info/LICENSE
fuocli-1.0.2.dist-info/METADATA
fuocli-1.0.2.dist-info/WHEEL
fuocli-1.0.2.dist-info/entry_points.txt
fuocli-1.0.2.dist-info/top_level.txt
fuocli-1.0.2.dist-info/RECORD
