Metadata-Version: 2.1
Name: fuocli
Version: 1.0.2
Summary: feeluown cli
Home-page: https://github.com/cosven/feeluown-cli
Author: Cosven
Author-email: cosven.yin@gmail.com
License: UNKNOWN
Keywords: toy
Platform: UNKNOWN
Classifier: Programming Language :: Python :: 3.5
Classifier: Programming Language :: Python :: 3.6
Classifier: Programming Language :: Python :: 3 :: Only
